cellect/__init__.py
cellect/_base_client.py
cellect/_client.py
cellect/_compat.py
cellect/_constants.py
cellect/_exceptions.py
cellect/_files.py
cellect/_models.py
cellect/_qs.py
cellect/_resource.py
cellect/_response.py
cellect/_streaming.py
cellect/_types.py
cellect/_version.py
cellect/py.typed
cellect/_utils/__init__.py
cellect/_utils/_compat.py
cellect/_utils/_datetime_parse.py
cellect/_utils/_logs.py
cellect/_utils/_proxy.py
cellect/_utils/_reflection.py
cellect/_utils/_resources_proxy.py
cellect/_utils/_streams.py
cellect/_utils/_sync.py
cellect/_utils/_transform.py
cellect/_utils/_typing.py
cellect/_utils/_utils.py
cellect/lib/.keep
cellect/resources/__init__.py
cellect/resources/api/__init__.py
cellect/resources/api/api.py
cellect/resources/api/v1/__init__.py
cellect/resources/api/v1/project.py
cellect/resources/api/v1/v1.py
cellect/types/__init__.py
cellect/types/api/__init__.py
cellect/types/api/v1_list_projects_params.py
cellect/types/api/v1_list_projects_response.py
cellect/types/api/v1_upload_file_params.py
cellect/types/api/v1/__init__.py
cellect/types/api/v1/project_apply_transform_params.py
cellect/types/api/v1/project_create_params.py
cellect/types/api/v1/project_download_params.py
cellect/types/api/v1/project_get_status_params.py
cellect/types/api/v1/project_response.py
cellect-0.5.0.dist-info/METADATA
cellect-0.5.0.dist-info/WHEEL
cellect-0.5.0.dist-info/licenses/LICENSE
cellect-0.5.0.dist-info/RECORD
